gwa-0.0.7.dist-info/METADATA
gwa-0.0.7.dist-info/WHEEL
gwa-0.0.7.dist-info/entry_points.txt
gwa-0.0.7.dist-info/licenses/LICENSE
gwa.libs/libcrypto-ab0b4425.so.3
gwa.libs/libssl-7d16d0d3.so.3
gwa/__init__.py
gwa/_core.abi3.so
gwa/_core.pyi
gwa/cli/__init__.py
gwa/cli/callbacks.py
gwa/cli/commands.py
gwa-0.0.7.dist-info/RECORD
