Metadata-Version: 2.4
Name: gwa
Version: 0.0.7
Classifier: Development Status :: 1 - Planning
Classifier: Intended Audience :: Developers
Classifier: Programming Language :: Python :: 3.10
Classifier: Programming Language :: Python :: 3.11
Classifier: Programming Language :: Python :: 3.12
Classifier: Programming Language :: Python :: 3.13
Classifier: Topic :: Software Development :: Code Generators
Classifier: Typing :: Typed
Classifier: License :: OSI Approved :: MIT License
Classifier: Topic :: Software Development :: Build Tools
Classifier: Topic :: Utilities
Requires-Dist: rich>=14.2.0
Requires-Dist: typer>=0.20.0
License-File: LICENSE
Summary: A command-line scaffolder for General Web App (GWA) projects.
Keywords: cli,scaffolding,template,web,fullstack
Author-email: Fernando Bryan Reza Campos <fer.rezac@outlook.com>
Requires-Python: >=3.10
Project-URL: Repository, https://github.com/Yrrrrrf/gwa-cli
Project-URL: Documentation, https://docs.rs/gwa
